GF_REPO
GF_VERSION
MANIFEST.in
README
gflib.py
setup.cfg
setup.py
/tmp/tmpzpojim/git-flow
/tmp/tmpzpojim/git-flow-feature
/tmp/tmpzpojim/git-flow-hotfix
/tmp/tmpzpojim/git-flow-init
/tmp/tmpzpojim/git-flow-release
/tmp/tmpzpojim/git-flow-support
/tmp/tmpzpojim/git-flow-version
/tmp/tmpzpojim/gitflow-common
/tmp/tmpzpojim/gitflow-shFlags
pygitflow.egg-info/PKG-INFO
pygitflow.egg-info/SOURCES.txt
pygitflow.egg-info/dependency_links.txt
pygitflow.egg-info/top_level.txt