Metadata-Version: 1.0
Name: pygitflow
Version: 1.0.0
Summary: Pythonic Installer for Git Flow.
Home-page: https://github.com/ampledata/pygitflow
Author: Greg Albrecht
Author-email: gba@splunk.com
License: Apache License 2.0
Platform: UNKNOWN
